shortml/__init__.py
shortml/classifier.py
shortml-0.0.2.dist-info/LICENCE.txt
shortml-0.0.2.dist-info/METADATA
shortml-0.0.2.dist-info/WHEEL
shortml-0.0.2.dist-info/top_level.txt
shortml-0.0.2.dist-info/RECORD
